odoo10_addon_attribute_set_mass_edit-10.0.1.0.1.99.dev6-py3.8-nspkg.pth
odoo/addons/attribute_set_mass_edit/README.rst
odoo/addons/attribute_set_mass_edit/__init__.py
odoo/addons/attribute_set_mass_edit/__manifest__.py
odoo/addons/attribute_set_mass_edit/models/__init__.py
odoo/addons/attribute_set_mass_edit/models/attribute_attribute.py
odoo/addons/attribute_set_mass_edit/models/attribute_group.py
odoo/addons/attribute_set_mass_edit/models/mass_object.py
odoo/addons/attribute_set_mass_edit/readme/CONTRIBUTORS.rst
odoo/addons/attribute_set_mass_edit/readme/DESCRIPTION.rst
odoo/addons/attribute_set_mass_edit/readme/USAGE.rst
odoo/addons/attribute_set_mass_edit/static/description/icon.png
odoo/addons/attribute_set_mass_edit/static/description/index.html
odoo/addons/attribute_set_mass_edit/tests/__init__.py
odoo/addons/attribute_set_mass_edit/tests/test_attribute_set_mass_edit.py
odoo/addons/attribute_set_mass_edit/views/attribute_attribute.xml
odoo10_addon_attribute_set_mass_edit-10.0.1.0.1.99.dev6.dist-info/METADATA
odoo10_addon_attribute_set_mass_edit-10.0.1.0.1.99.dev6.dist-info/WHEEL
odoo10_addon_attribute_set_mass_edit-10.0.1.0.1.99.dev6.dist-info/namespace_packages.txt
odoo10_addon_attribute_set_mass_edit-10.0.1.0.1.99.dev6.dist-info/top_level.txt
odoo10_addon_attribute_set_mass_edit-10.0.1.0.1.99.dev6.dist-info/RECORD
